algo_python/__init__.py
algo_python-1.dist-info/licenses/LICENCE.md
algo_python-1.dist-info/METADATA
algo_python-1.dist-info/WHEEL
algo_python-1.dist-info/top_level.txt
algo_python-1.dist-info/RECORD
