Metadata-Version: 2.4
Name: algo_python
Version: 1
Summary: Python package for controlling robot via serial commands
Author-email: Tarik Subasic <tarik.subasic@microbitdesign.com>
Classifier: License :: OSI Approved :: MIT License
Requires-Python: >=3.0
License-File: LICENCE.md
Requires-Dist: pyserial
Dynamic: license-file
